{
	"schemaVersion": 1,
	"id": "afamiliarmaw",
	"version": "${version}",
	"name": "the Magnificent Maw",
	"description": "a Curious Vial, and a few tricks with your Maw. remember to Breathe!",
	"authors": [
		"afamiliarquiet"
	],
	"contact": {
		"homepage": "https://github.com/afamiliarquiet/afamiliarmaw",
		"sources": "https://github.com/afamiliarquiet/afamiliarmaw"
	},
	"license": "CC0-1.0",
	"icon": "assets/afamiliarmaw/icon.png",
	"environment": "*",
	"entrypoints": {
		"main": [
          "io.github.afamiliarquiet.AFamiliarMaw"
		],
		"client": [
			"io.github.afamiliarquiet.AFamiliarMawClient"
		],
		"fabric-datagen": [
			"io.github.afamiliarquiet.AFamiliarMawDataGenerator"
		]
	},
	"mixins": [
		"afamiliarmaw.mixins.json",
		{
			"config": "afamiliarmaw.client.mixins.json",
			"environment": "client"
		}
	],
	"depends": {
		"fabricloader": ">=0.15.11",
		"minecraft": "~1.21-",
		"java": ">=21",
		"fabric-api": "*"
	},
	"suggests": {
		"another-mod": "*"
	}
}